{
    "name": "maqueen",
    "version": "1.7.0",
    "description": "Affordable mini robot designed by DFRobot",
    "license": "MIT",
    "dependencies": {
        "core": "*",
        "ir": "github:tangjie133/pxt-DFRobot_IR#v0.0.7"
    },
    "files": [
        "main.ts",
        "_locales/zh-cn/maqueen-strings.json"
    ],
    "testFiles": [
        "test.ts"
    ],
    "public": true,
    "targetVersions": {
        "target": "4.0.16",
        "targetId": "microbit"
    },
    "supportedTargets": [
        "microbit"
    ],
    "preferredEditor": "tsprj"
}
